[
  {
    "name": "faking kvader",
    "mirror": false,
    "x": 0,
    "y": -63.10432569974555,
    "z": 47.837150127226465,
    "sx": 20.356234096692113,
    "sy": 22.391857506361326,
    "sz": 20.356234096692113,
    "r": 0,
    "g": 0,
    "b": 0
  },
  {
    "name": "faking kvader",
    "mirror": false,
    "x": 0,
    "y": -63.10432569974555,
    "z": 96.69211195928754,
    "sx": 20.356234096692113,
    "sy": 22.391857506361326,
    "sz": 20.356234096692113,
    "r": 0,
    "g": 0,
    "b": 0
  },
  {
    "name": "faking kvader",
    "mirror": false,
    "x": 0,
    "y": -52.9262086513995,
    "z": 157.76081424936388,
    "sx": 20.356234096692113,
    "sy": 22.391857506361326,
    "sz": 20.356234096692113,
    "r": 0,
    "g": 0,
    "b": 0
  },
  {
    "name": "faking kvader",
    "mirror": false,
    "x": 0,
    "y": -52.9262086513995,
    "z": 196.43765903307892,
    "sx": 20.356234096692113,
    "sy": 22.391857506361326,
    "sz": 20.356234096692113,
    "r": 0,
    "g": 0,
    "b": 0
  },
  {
    "name": "faking kvader",
    "mirror": false,
    "x": -18.3206106870229,
    "y": -45.80152671755726,
    "z": 279.89821882951657,
    "sx": 12.213740458015268,
    "sy": 2.035623409669211,
    "sz": 40.712468193384225,
    "r": 0,
    "g": 0,
    "b": 0
  },
  {
    "name": "faking kvader",
    "mirror": false,
    "x": 16.28498727735369,
    "y": -47.837150127226465,
    "z": 279.89821882951657,
    "sx": 12.213740458015268,
    "sy": 2.035623409669211,
    "sz": 40.712468193384225,
    "r": 0,
    "g": 0,
    "b": 0
  },
  {
    "name": "faking kvader",
    "mirror": false,
    "x": 0,
    "y": -43.765903307888046,
    "z": 245.29262086514,
    "sx": 18.3206106870229,
    "sy": 2.035623409669211,
    "sz": 4.071246819338422,
    "r": 0,
    "g": 0,
    "b": 0
  },
  {
    "name": "faking kvader",
    "mirror": false,
    "x": 0,
    "y": 0,
    "z": 58.015267175572525,
    "sx": 130.27989821882952,
    "sy": 132.31552162849874,
    "sz": 124.17302798982192,
    "r": 255,
    "g": 255,
    "b": 255
  },
  {
    "name": "faking kvader",
    "mirror": false,
    "x": 0,
    "y": 0,
    "z": 169.97455470737913,
    "sx": 103.81679389312978,
    "sy": 107.88804071246821,
    "sz": 105.852417302799,
    "r": 255,
    "g": 255,
    "b": 255
  },
  {
    "name": "faking kvader",
    "mirror": false,
    "x": 0,
    "y": 0,
    "z": 267.6844783715013,
    "sx": 85.49618320610688,
    "sy": 85.49618320610688,
    "sz": 105.852417302799,
    "r": 255,
    "g": 255,
    "b": 255
  },
  {
    "name": "faking kvader",
    "mirror": false,
    "x": 0,
    "y": 0,
    "z": 316.5394402035624,
    "sx": 111.95928753180664,
    "sy": 109.92366412213742,
    "sz": 14.24936386768448,
    "r": 0,
    "g": 0,
    "b": 0
  },
  {
    "name": "faking kvader",
    "mirror": false,
    "x": 0,
    "y": 0,
    "z": 182.1882951653944,
    "sx": 225.95419847328245,
    "sy": 16.28498727735369,
    "sz": 14.24936386768448,
    "r": 0,
    "g": 0,
    "b": 0
  },
  {
    "name": "faking kvader",
    "mirror": false,
    "x": 0,
    "y": 0,
    "z": 347.07379134860054,
    "sx": 75.31806615776081,
    "sy": 79.38931297709924,
    "sz": 52.9262086513995,
    "r": 0,
    "g": 0,
    "b": 0
  }
]